setup.py
LABULAC/__init__.py
LABULAC/labulac.py
labulac/__init__.py
labulac/labulac.py
labulac.egg-info/PKG-INFO
labulac.egg-info/SOURCES.txt
labulac.egg-info/dependency_links.txt
labulac.egg-info/entry_points.txt
labulac.egg-info/requires.txt
labulac.egg-info/top_level.txt
labulac.egg-info/zip-safe