Metadata-Version: 1.0
Name: labulac
Version: 0.2.3
Summary: firs tool
Home-page: https://github.com/labulac/labulac
Author: cms
Author-email: 740162752@qq.com
License: MIT Licence
Keywords: pip,labulac,labula
Platform: any
